upd_agent/__init__.py
upd_agent-0.1.1.dist-info/METADATA
upd_agent-0.1.1.dist-info/WHEEL
upd_agent-0.1.1.dist-info/entry_points.txt
upd_agent-0.1.1.dist-info/RECORD
